{
  "preset": "Default",
  "remembered": {
    "Default": {
      "0": {
        "scene": "none",
        "animation": 0,
        "mode": 0,
        "pointShape": 1,
        "pointSize": 8,
        "lineShape": "line",
        "deformation": false,
        "deformationProgress": 0,
        "bgColor": 0,
        "zPosition": 4.5,
        "pointer": false,
        "accel": false,
        "rotation": false,
        "capture": false,
        "stopMotion": false,
        "particleAlpha": 0,
        "inputAudio": false,
        "audio": null,
        "detector": false,
        "effect": "none",
        "video": null,
        "videoZoom": 1,
        "videoAlpha": 1
      }
    },
    "Post Effect": {
      "0": {
        "scene": "none",
        "animation": 0,
        "mode": 0,
        "pointShape": 1,
        "pointSize": 8,
        "lineShape": "line",
        "deformation": false,
        "deformationProgress": 0,
        "bgColor": 0,
        "zPosition": 4.5,
        "pointer": false,
        "accel": false,
        "rotation": false,
        "capture": false,
        "stopMotion": false,
        "particleAlpha": 0,
        "inputAudio": false,
        "audio": null,
        "detector": false,
        "effect": "none",
        "video": null,
        "videoZoom": 1,
        "videoAlpha": 1
      }
    },
    "Particle": {
      "0": {
        "scene": "Particle",
        "animation": 0,
        "mode": 0,
        "pointShape": 1,
        "pointSize": 8,
        "lineShape": "line",
        "deformation": false,
        "deformationProgress": 0,
        "bgColor": 0,
        "zPosition": 4.5,
        "pointer": false,
        "accel": false,
        "rotation": false,
        "capture": false,
        "stopMotion": false,
        "particleAlpha": 1,
        "inputAudio": false,
        "audio": null,
        "detector": false,
        "effect": "none",
        "video": null,
        "videoZoom": 1,
        "videoAlpha": 0
      }
    },
    "Warp": {
      "0": {
        "scene": "Particle",
        "animation": 1,
        "mode": 0,
        "pointShape": 1,
        "pointSize": 5,
        "lineShape": "line",
        "deformation": false,
        "deformationProgress": 0,
        "bgColor": 0,
        "zPosition": 4.5,
        "pointer": false,
        "accel": false,
        "rotation": false,
        "capture": false,
        "stopMotion": false,
        "particleAlpha": 1,
        "inputAudio": false,
        "audio": null,
        "detector": false,
        "effect": "none",
        "video": null,
        "videoZoom": 1,
        "videoAlpha": 0.5
      }
    },
    "Pop": {
      "0": {
        "scene": "Pop",
        "animation": 0,
        "mode": 0,
        "pointShape": 1,
        "pointSize": 5,
        "lineShape": "line",
        "deformation": false,
        "deformationProgress": 0,
        "bgColor": 1,
        "zPosition": 4.5,
        "pointer": true,
        "accel": false,
        "rotation": false,
        "capture": false,
        "stopMotion": false,
        "particleAlpha": 1,
        "inputAudio": false,
        "audio": null,
        "detector": false,
        "effect": "none",
        "video": null,
        "videoZoom": 1,
        "videoAlpha": 0
      }
    }
  },
  "closed": false,
  "folders": {
    "Particle": {
      "preset": "Default",
      "closed": false,
      "folders": {
        "gl.POINTS": {
          "preset": "Default",
          "closed": false,
          "folders": {}
        },
        "gl.LINE_STRIP": {
          "preset": "Default",
          "closed": true,
          "folders": {}
        },
        "canvas": {
          "preset": "Default",
          "closed": false,
          "folders": {}
        },
        "video": {
          "preset": "Default",
          "closed": false,
          "folders": {}
        },
        "audio": {
          "preset": "Default",
          "closed": false,
          "folders": {}
        }
      }
    },
    "Post Effect": {
      "preset": "Default",
      "closed": false,
      "folders": {}
    }
  }
}
